Metadata-Version: 1.1
Name: CanvasSync
Version: 0.2.4
Summary: Synchronizes modules, assignments and files from a Canvas server to a local folder
Home-page: https://github.com/perslev/CanvasSync
Author: Mathias Perslev
Author-email: mathias@perslev.com
License: LICENSE.txt
Platform: UNKNOWN
Classifier: Development Status :: 3 - Alpha
Classifier: Environment :: Console
Classifier: Operating System :: MacOS :: MacOS X
Classifier: Operating System :: POSIX
Classifier: Programming Language :: Python
Classifier: License :: OSI Approved :: MIT License
